aastex/__init__.py
aastex/_aastex.py
aastex/_formatting.py
aastex/_tests/__init__.py
aastex/_tests/test_aastex.py
aastex-0.3.1.dist-info/METADATA
aastex-0.3.1.dist-info/WHEEL
aastex-0.3.1.dist-info/top_level.txt
aastex-0.3.1.dist-info/RECORD
