Metadata-Version: 2.1
Name: aastex
Version: 0.3.1
Summary: A Python wrapper around the AASTeX Latex packages
Author-email: "Roy T. Smart" <roytsmart@gmail.com>
Project-URL: Homepage, https://github.com/sun-data/aastex
Project-URL: Documentation, https://aastex.readthedocs.io/en/latest
Classifier: Programming Language :: Python :: 3
Requires-Python: >=3.10
Requires-Dist: pylatex
Requires-Dist: numpy
Requires-Dist: matplotlib
Requires-Dist: astropy
Provides-Extra: doc
Requires-Dist: pytest ; extra == 'doc'
Requires-Dist: graphviz ; extra == 'doc'
Requires-Dist: sphinx-autodoc-typehints ; extra == 'doc'
Requires-Dist: pydata-sphinx-theme ; extra == 'doc'
Requires-Dist: ipykernel ; extra == 'doc'
Requires-Dist: jupyter-sphinx ; extra == 'doc'
Requires-Dist: sphinx-favicon ; extra == 'doc'
Provides-Extra: test
Requires-Dist: pytest ; extra == 'test'
